Workbook

Sheet 🏠 Instruções
B1: FIAP — Modelo de Projeção Financeira para Startups (MVP)
B3: Projeção 3 Anos · Indicadores para Investidores
B5: 📌 LEGENDA DE CORES
B6: Células AMARELAS | C6: ← Preencha aqui! São os dados de entrada da sua startup
B7: Texto AZUL | C7: ← Valores que você deve inserir (inputs / premissas)
B8: Texto PRETO | C8: ← Fórmulas calculadas automaticamente. Não edite.
B9: Texto VERDE | C9: ← Dados que vêm de outra aba (cross-reference).
B12: 📖 PASSO A PASSO
B13: 1. 📋 Premissas | C13: Preencha os dados AZUL: modelo de receita, preço, crescimento de clientes, churn e investimento inicial.
B14: 2. 💸 Despesas | C14: Informe os principais blocos de custo da sua operação nos 3 anos.
B15: 3. 📊 Projeção 3 Anos | C15: Gerada automaticamente com base nas suas premissas. Confira receita, lucro e fluxo de caixa.
B16: 4. 🚀 Dashboard Inv. | C16: Painel automático com os KPIs que investidores analisam: MRR, CAC, LTV, Churn, Runway e mais.
B19: ⚠️ IMPORTANTE
B20: Horizonte: | C20: Esta planilha cobre 3 anos (Ano 1 → Ano 3). Suficiente para avaliar viabilidade em estágio MVP/Seed.
B21: Formato moeda: | C21: Todos os valores em R$ (Reais). Ajuste o ticket médio conforme seu mercado.
B22: Modelo de receita: | C22: O modelo usa lógica de recorrência (SaaS/assinatura). Adapte o ticket para outros modelos.

Sheet 📋 Premissas
B1: 📋 PREMISSAS DO NEGÓCIO — preencha apenas as células amarelas
B2: Células ROSA = você preenche | Células CINZAS = calculadas automaticamente | Células VERDES = vêm de outra aba
B4: Premissa / Item | C4: ANO 1 | D4: ANO 2 | E4: ANO 3 | F4: Dica para preencher
B6: 💰 RECEITA — LINHA 1 (principal fonte de receita do seu negócio) | F6: Ex: assinatura mensal, venda de produto, taxa por uso
B7: Nome / descrição da receita | C7: Assinatura SaaS AllStay | D7: Assinatura SaaS AllStay | E7: Assinatura SaaS AllStay | F7: Descreva o que o cliente paga (ex: mensalidade, comissão, licença)
B8: Ticket médio por cliente / transação (R$) | C8: 7500 | D8: 7500 | E8: 7500 | F8: Quanto cada cliente paga por mês (ou por compra/uso)
B9: Novos clientes conquistados por mês | C9: 0.59202386 | D9: 1.1621667 | E9: 1.7472382 | F9: Média mensal necessária para atingir a base ativa projetada, considerando churn de 1/15 ao mês.
B10: % Churn — clientes que cancelam por mês | C10: 0.066666667 | D10: 0.066666667 | E10: 0.066666667 | F10: Permanência média de 15 meses: churn mensal aproximado = 1/15 = 6,67%.
B11: ▸ Clientes ativos ao final do ano | C11: =C9*(1-C10)*0+C9*((1-(1-C10)^12)/C10) -> 5 | D11: =C11*(1-D10)^12+D9*((1-(1-D10)^12)/D10) -> 12 | E11: =D11*(1-E10)^12+E9*((1-(1-E10)^12)/E10) -> 20 | F11: Calculado: novos clientes menos cancelamentos ao longo do ano
B12: ▸ Receita Anual — Linha 1 (R$) | C12: =C11*C8*12 -> 450000 | D12: =D11*D8*12 -> 1080000 | E12: =E11*E8*12 -> 1800000 | F12: Receita anual = clientes ativos × ticket × 12 meses
B14: 💰 RECEITA — LINHA 2 (segunda fonte de receita — opcional) | F14: Ex: consultoria, venda avulsa, comissão. Deixe zero se não tiver.
B15: Nome / descrição da receita 2 | C15: Contrato Enterprise Customizado | D15: Contrato Enterprise Customizado | E15: Contrato Enterprise Customizado | F15: Se não tiver 2ª receita, deixe os valores abaixo como zero
B16: Ticket médio por cliente / transação (R$) | C16: 0 | D16: 0 | E16: 100000 | F16: Valor médio recebido por cliente/projeto desta linha
B17: Clientes ou transações por mês | C17: 0 | D17: 0 | E17: 1 | F17: Número de contratos Enterprise Customizados ativos no mês.
B18: ▸ Receita Anual — Linha 2 (R$) | C18: =C16*C17*12 -> 0 | D18: =D16*D17*12 -> 0 | E18: =E16*E17*12 -> 1200000 | F18: Receita anual = ticket × transações/mês × 12
B19: ▸ RECEITA TOTAL ANUAL (R$) | C19: =C12+C18 -> 450000 | D19: =D12+D18 -> 1080000 | E19: =E12+E18 -> 3000000 | F19: Soma automática das duas linhas de receita
B21: 💸 CUSTOS OPERACIONAIS — quanto você gasta por mês (R$) | F21: Preencha os valores mensais de cada categoria de custo
B22: Categoria de Custo | C22: ANO 1 /mês | D22: ANO 2 /mês | E22: ANO 3 /mês | F22: O que incluir aqui?
B23: 👥 Pessoal (salários + encargos) | C23: 77000 | D23: 104500 | E23: 154500 | F23: Sócios pró-labore, funcionários, freelancers. Inclua INSS e FGTS (~30% do salário bruto)
B24: 📣 Marketing e Aquisição de Clientes | C24: 8333.3333 | D24: 8333.3333 | E24: 8333.3333 | F24: Eventos, feiras e prospecção B2B; R$100 mil/ano.
B25: 🤝 Vendas e Comissões | C25: 0 | D25: 0 | E25: 0 | F25: Comissões separadas não consideradas; equipe comercial está em Pessoal.
B26: 🖥️ Tecnologia e Infraestrutura (Tech) | C26: 7500 | D26: 11000 | E26: 15000 | F26: Cloud/servidores (AWS, GCP), APIs, ferramentas de dev, domínio, SaaS usados
B27: 🏢 Administrativo (G&A) | C27: 4000 | D27: 8666.6667 | E27: 10666.667 | F27: Aluguel, contador, advogado, internet, softwares de escritório, material
B28: 🧾 Impostos sobre receita (%) | C28: 0 | D28: 0 | E28: 0.085 | F28: Tributação não incluída nesta projeção de EBITDA; validar regime tributário posteriormente.
B29: ▸ Total Custo Operacional/mês (R$) | C29: =C23+C24+C25+C26+C27 -> 96833.333 | D29: =D23+D24+D25+D26+D27 -> 132500 | E29: =E23+E24+E25+E26+E27 -> 188500 | F29: Soma automática de todas as categorias (sem impostos)
B30: ▸ Impostos sobre receita (R$) | C30: =C19*C28 -> 0 | D30: =D19*D28 -> 0 | E30: =E19*E28 -> 255000 | F30: Calculado: receita total × % de imposto informado acima
B32: 🚀 INVESTIMENTO INICIAL E CAPTAÇÃO | F32: O que você precisa para começar e de onde vem o dinheiro
B33: Investimento inicial em tecnologia/produto (R$) | C33: 130000 | D33: 0 | E33: 0 | F33: MVP (R$100 mil) + infraestrutura inicial do MVP (R$30 mil).
B34: Investimento inicial em marketing/lançamento (R$) | C34: 50000 | D34: 0 | E34: 0 | F34: Eventos de lançamento e estruturação comercial B2B.
B35: Outros investimentos iniciais (R$) | C35: 20000 | D35: 0 | E35: 0 | F35: Constituição da empresa e apoio jurídico inicial.
B36: ▸ Total de Investimento no Ano (R$) | C36: =C33+C34+C35 -> 200000 | D36: =D33+D34+D35 -> 0 | E36: =E33+E34+E35 -> 0 | F36: Soma dos três itens acima
B37: Capital próprio disponível (R$) | C37: 1000000 | D37: 0 | E37: 0 | F37: Aporte inicial total: CAPEX + capital de giro + reserva de contingência = R$2,553 milhões.
B38: Captação externa prevista no ano (R$) | D38: 1553000 | E38: 0 | F38: Anjo, Seed, FAPESP, BNDES — coloque 0 se não há previsão
B40: 📐 MARGEM BRUTA — custo direto do que você entrega | F40: COGS = custo direto de cada produto/serviço vendido (sem contar estrutura)
B41: % do custo direto sobre a receita (COGS %) | C41: 0 | D41: 0 | E41: 0 | F41: Ex: hosting por cliente, mão de obra por projeto, custo de produto. Benchmark SaaS: 20–35%
B42: ▸ Margem Bruta % (calculada) | C42: =1-C41 -> 1 | D42: =1-D41 -> 1 | E42: =1-E41 -> 1 | F42: Saudavel: acima de 60%

Sheet 📊 Projeção 3 Anos
B1: 📊 PROJEÇÃO FINANCEIRA — 3 ANOS
B2: Calculado automaticamente com base nas premissas | Não edite esta aba
B4: Linha Financeira | C4: ANO 1 | D4: ANO 2 | E4: ANO 3 | F4: Var. Ano1→3
B6: 💰 RECEITA
B7: Receita Linha 1 (R$) | C7: ='📋 Premissas'!C12 -> 450000 | D7: ='📋 Premissas'!D12 -> 1080000 | E7: ='📋 Premissas'!E12 -> 1800000 | F7: =IF(C7<>0,(E7-C7)/ABS(C7),0) -> 3
B8: Receita Linha 2 (R$) | C8: ='📋 Premissas'!C18 -> 0 | D8: ='📋 Premissas'!D18 -> 0 | E8: ='📋 Premissas'!E18 -> 1200000 | F8: =IF(C8<>0,(E8-C8)/ABS(C8),0) -> 0
B9: RECEITA TOTAL (R$) | C9: =C7+C8 -> 450000 | D9: =D7+D8 -> 1080000 | E9: =E7+E8 -> 3000000 | F9: =IF(C9<>0,(E9-C9)/ABS(C9),0) -> 5.6666667
B11: 💸 CUSTOS E DESPESAS
B12: (-) COGS — Custo Direto do Serviço/Produto (R$) | C12: =-'📋 Premissas'!C41*C9 -> 0 | D12: =-'📋 Premissas'!D41*D9 -> 0 | E12: =-'📋 Premissas'!E41*E9 -> 0 | F12: =IF(C12<>0,(E12-C12)/ABS(C12),0) -> 0
B13: LUCRO BRUTO (R$) | C13: =C9+C12 -> 450000 | D13: =D9+D12 -> 1080000 | E13: =E9+E12 -> 3000000 | F13: =IF(C13<>0,(E13-C13)/ABS(C13),0) -> 5.6666667
B14: Margem Bruta % | C14: =IF(C9<>0,C13/C9,0) -> 1 | D14: =IF(D9<>0,D13/D9,0) -> 1 | E14: =IF(E9<>0,E13/E9,0) -> 1
B15: (-) Pessoal — salários e encargos (R$) | C15: =-'📋 Premissas'!C23*12 -> -924000 | D15: =-'📋 Premissas'!D23*12 -> -1254000 | E15: =-'📋 Premissas'!E23*12 -> -1854000 | F15: =IF(C15<>0,(E15-C15)/ABS(C15),0) -> -1.0064935
B16: (-) Marketing e Aquisição (R$) | C16: =-'📋 Premissas'!C24*12 -> -100000 | D16: =-'📋 Premissas'!D24*12 -> -100000 | E16: =-'📋 Premissas'!E24*12 -> -100000 | F16: =IF(C16<>0,(E16-C16)/ABS(C16),0) -> 0
B17: (-) Vendas e Comissões (R$) | C17: =-'📋 Premissas'!C25*12 -> 0 | D17: =-'📋 Premissas'!D25*12 -> 0 | E17: =-'📋 Premissas'!E25*12 -> 0 | F17: =IF(C17<>0,(E17-C17)/ABS(C17),0) -> 0
B18: (-) Tecnologia e Infra (R$) | C18: =-'📋 Premissas'!C26*12 -> -90000 | D18: =-'📋 Premissas'!D26*12 -> -132000 | E18: =-'📋 Premissas'!E26*12 -> -180000 | F18: =IF(C18<>0,(E18-C18)/ABS(C18),0) -> -1
B19: (-) Administrativo / G&A (R$) | C19: =-'📋 Premissas'!C27*12 -> -48000 | D19: =-'📋 Premissas'!D27*12 -> -104000 | E19: =-'📋 Premissas'!E27*12 -> -128000 | F19: =IF(C19<>0,(E19-C19)/ABS(C19),0) -> -1.6666667
B20: (-) Impostos sobre Receita (R$) | C20: =-'📋 Premissas'!C30 -> 0 | D20: =-'📋 Premissas'!D30 -> 0 | E20: =-'📋 Premissas'!E30 -> -255000 | F20: =IF(C20<>0,(E20-C20)/ABS(C20),0) -> 0
B21: EBITDA — Resultado Operacional (R$) | C21: =C13+C15+C16+C17+C18+C19+C20 -> -712000 | D21: =D13+D15+D16+D17+D18+D19+D20 -> -510000 | E21: =E13+E15+E16+E17+E18+E19+E20 -> 483000 | F21: =IF(ABS(C21)>0,(E21-C21)/ABS(C21),0) -> 1.6783708
B22: EBITDA Margin % | C22: =IF(C9<>0,C21/C9,0) -> -1.5822222 | D22: =IF(D9<>0,D21/D9,0) -> -0.47222222 | E22: =IF(E9<>0,E21/E9,0) -> 0.161
B24: 🏦 FLUXO DE CAIXA SIMPLIFICADO
B25: Caixa no início do ano (R$) | C25: ='📋 Premissas'!C37 -> 1000000 | D25: =C28 -> 88000 | E25: =D28 -> 1131000
B26: (+) Captação externa / Aporte (R$) | C26: ='📋 Premissas'!C38 -> 0 | D26: ='📋 Premissas'!D38 -> 1553000 | E26: ='📋 Premissas'!E38 -> 0
B27: (-) Investimento / Capex (R$) | C27: =-'📋 Premissas'!C36 -> -200000 | D27: =-'📋 Premissas'!D36 -> 0 | E27: =-'📋 Premissas'!E36 -> 0
B28: CAIXA FINAL DO ANO (R$) | C28: =C25+C26+C27+C21 -> 88000 | D28: =D25+D26+D27+D21 -> 1131000 | E28: =E25+E26+E27+E21 -> 1614000
B29: Runway — meses de vida do caixa | C29: =IF(C21<0,C28/ABS(C21)*12,999) -> 1.4831461 | D29: =IF(D21<0,D28/ABS(D21)*12,999) -> 26.611765 | E29: =IF(E21<0,E28/ABS(E21)*12,999) -> 999

Sheet 🚀 Dashboard Investidor
B1: 🚀 DASHBOARD DO INVESTIDOR — KPIs de Startup em MVP
B2: Calculado automaticamente a partir das suas premissas | Benchmarks: mercado SaaS/Tech Brasil
B4: VISÃO GERAL — ANO 3
B5: Receita Anual (ARR) | D5: Clientes Ativos | G5: Margem Bruta %
B6: ='📊 Projeção 3 Anos'!E9 -> 3000000 | D6: ='📋 Premissas'!E11 -> 20 | G6: =1-'📋 Premissas'!E41 -> 1
B7: Meta: > R$1M | D7: Meta: > 300 | G7: > 60%
B9: INDICADORES DETALHADOS — OS NÚMEROS QUE INVESTIDORES ANALISAM
B10: KPI | C10: ANO 1 | D10: ANO 2 | E10: ANO 3 | G10: O que significa? | H10: Benchmark | I10: Status (Ano 3)
B11: MRR — Receita Recorrente Mensal | C11: ='📊 Projeção 3 Anos'!C9/12 -> 37500 | D11: ='📊 Projeção 3 Anos'!D9/12 -> 90000 | E11: ='📊 Projeção 3 Anos'!E9/12 -> 250000 | G11: Receita mensal recorrente — principal termômetro de crescimento | H11: > R$50K Ano2 / > R$80K Ano3 | I11: =IF('📊 Projeção 3 Anos'!E9/12>=80000,"✅ Ótimo",IF('📊 Projeção 3 Anos'!E9/12>=30000,"🟡 Em crescimento","🔴 Abaixo")) -> ✅ Ótimo
B12: ARR — Receita Anual Recorrente | C12: ='📊 Projeção 3 Anos'!C9 -> 450000 | D12: ='📊 Projeção 3 Anos'!D9 -> 1080000 | E12: ='📊 Projeção 3 Anos'!E9 -> 3000000 | G12: ARR = MRR × 12 — define o 'tamanho' do negócio para o investidor | H12: > R$500K Ano2 / > R$1M Ano3 | I12: =IF('📊 Projeção 3 Anos'!E9>=1000000,"✅ Ótimo",IF('📊 Projeção 3 Anos'!E9>=300000,"🟡 Em crescimento","🔴 Abaixo")) -> ✅ Ótimo
B13: Clientes Ativos | C13: ='📋 Premissas'!C11 -> 5 | D13: ='📋 Premissas'!D11 -> 12 | E13: ='📋 Premissas'!E11 -> 20 | G13: Base de clientes pagantes — prova de tração do produto | H13: > 100 Ano1 / > 300 Ano3 | I13: =IF('📋 Premissas'!E11>=300,"✅ Ótimo",IF('📋 Premissas'!E11>=100,"🟡 Ok","🔴 Abaixo")) -> 🔴 Abaixo
B14: Churn Mensal % | C14: ='📋 Premissas'!C10 -> 0.066666667 | D14: ='📋 Premissas'!D10 -> 0.066666667 | E14: ='📋 Premissas'!E10 -> 0.066666667 | G14: % de clientes perdidos/mês — quanto menor, melhor o produto | H14: < 3%/mês (SaaS B2B) / < 5% (B2C) | I14: =IF('📋 Premissas'!E10<=0.02,"✅ Ótimo",IF('📋 Premissas'!E10<=0.04,"🟡 Aceitável","🔴 Alto")) -> 🔴 Alto
B15: CAC — Custo por Cliente (R$) | C15: 24000 | D15: 24000 | E15: 24000 | G15: Quanto custa adquirir 1 cliente — deve cair ao longo do tempo | H15: Deve ser < LTV/3 | I15: "-"
B16: LTV — Valor do Cliente (R$) | C16: =IF('📋 Premissas'!C10>0,'📋 Premissas'!C8/'📋 Premissas'!C10,0) -> 112500 | D16: =IF('📋 Premissas'!D10>0,'📋 Premissas'!D8/'📋 Premissas'!D10,0) -> 112500 | E16: =IF('📋 Premissas'!E10>0,'📋 Premissas'!E8/'📋 Premissas'!E10,0) -> 112500 | G16: Receita total esperada por cliente enquanto ele ficar ativo | H16: > 3× o CAC (mínimo) | I16: "-"
B17: LTV / CAC | C17: =IF(C15>0,C16/C15,0) -> 4.6875 | D17: =IF(D15>0,D16/D15,0) -> 4.6875 | E17: =IF(E15>0,E16/E15,0) -> 4.6875 | G17: Retorno sobre custo de aquisição — > 3x = modelo sustentável | H17: > 3x aceitável / > 5x excelente | I17: =IF(IF(IF('📋 Premissas'!E9>0,('📋 Premissas'!E24+'📋 Premissas'!E25)/'📋 Premissas'!E9,0)>0,IF('📋 Premissas'!E10>0,'📋 Premissas'!E8/'📋 Premissas'!E10,0)/IF('📋 Premissas'!E9>0,('📋 Premissas'!E24+'📋 Premissas'!E25)/'📋 Premissas'!E9,0),0)>=5,"✅ Excelente",IF(IF(IF('📋 Premissas'!E9>0,('📋 Premissas'!E24+'📋 Premissas'!E25)/'📋 Premissas'!E9,0)>0,IF('📋 Premissas'!E10>0,'📋 Premissas'!E8/'📋 Premissas'!E10,0)/IF('📋 Premissas'!E9>0,('📋 Premissas'!E24+'📋 Premissas'!E25)/'📋 Premissas'!E9,0),0)>=3,"🟡 Aceitável","🔴 Atenção")) -> ✅ Excelente
B18: Payback (meses) | C18: =IF(C15>0,C15/'📋 Premissas'!C8,0) -> 3.2 | D18: =IF(D15>0,D15/'📋 Premissas'!D8,0) -> 3.2 | E18: =IF(E15>0,E15/'📋 Premissas'!E8,0) -> 3.2 | G18: Meses para recuperar o CAC — quanto menor, mais eficiente | H18: < 12 meses / Ideal: < 6 meses | I18: =IF(IF('📋 Premissas'!E8>0,IF('📋 Premissas'!E9>0,('📋 Premissas'!E24+'📋 Premissas'!E25)/'📋 Premissas'!E9,0)/'📋 Premissas'!E8,0)<=6,"✅ Rápido",IF(IF('📋 Premissas'!E8>0,IF('📋 Premissas'!E9>0,('📋 Premissas'!E24+'📋 Premissas'!E25)/'📋 Premissas'!E9,0)/'📋 Premissas'!E8,0)<=12,"🟡 Ok","🔴 Lento")) -> ✅ Rápido
B19: Margem Bruta % | C19: =1-'📋 Premissas'!C41 -> 1 | D19: =1-'📋 Premissas'!D41 -> 1 | E19: =1-'📋 Premissas'!E41 -> 1 | G19: % da receita que sobra após custos diretos — indica escalabilidade | H19: 60–80% SaaS / > 50% outros | I19: =IF(1-'📋 Premissas'!E41>=0.6,"✅ Saudável",IF(1-'📋 Premissas'!E41>=0.4,"🟡 Ok","🔴 Baixa")) -> ✅ Saudável
B20: EBITDA (R$) | C20: ='📊 Projeção 3 Anos'!C21 -> -712000 | D20: ='📊 Projeção 3 Anos'!D21 -> -510000 | E20: ='📊 Projeção 3 Anos'!E21 -> 483000 | G20: Resultado operacional — negativo no início é normal, deve virar positivo | H20: Positivo a partir do Ano 2 ou 3 | I20: =IF('📊 Projeção 3 Anos'!E21>0,"✅ Lucrativo","🔴 Queimando caixa") -> ✅ Lucrativo
B21: EBITDA Margin % | C21: ='📊 Projeção 3 Anos'!C22 -> -1.5822222 | D21: ='📊 Projeção 3 Anos'!D22 -> -0.47222222 | E21: ='📊 Projeção 3 Anos'!E22 -> 0.161 | G21: % do faturamento que vira lucro operacional | H21: > 15% no Ano 3 | I21: =IF('📊 Projeção 3 Anos'!E22>=0.15,"✅ Saudável",IF('📊 Projeção 3 Anos'!E22>=0,"🟡 Break-even","🔴 Negativo")) -> ✅ Saudável
B22: Runway (meses de caixa) | C22: ='📊 Projeção 3 Anos'!C29 -> 1.4831461 | D22: ='📊 Projeção 3 Anos'!D29 -> 26.611765 | E22: ='📊 Projeção 3 Anos'!E29 -> 999 | G22: Quantos meses o caixa dura — abaixo de 12 = zona de perigo | H22: > 18 meses sempre | I22: =IF('📊 Projeção 3 Anos'!E29>=18,"✅ Confortável",IF('📊 Projeção 3 Anos'!E29>=12,"🟡 Ok","🔴 Crítico")) -> ✅ Confortável
B23: Crescimento de Receita YoY % | C23: "-" | D23: =IF('📊 Projeção 3 Anos'!C9>0,('📊 Projeção 3 Anos'!D9-'📊 Projeção 3 Anos'!C9)/'📊 Projeção 3 Anos'!C9,0) -> 1.4 | E23: =IF('📊 Projeção 3 Anos'!D9>0,('📊 Projeção 3 Anos'!E9-'📊 Projeção 3 Anos'!D9)/'📊 Projeção 3 Anos'!D9,0) -> 1.7777778 | G23: Taxa de crescimento da receita ano a ano — crucial para VC | H23: > 100% Ano2 / > 80% Ano3 | I23: =IF(IF('📊 Projeção 3 Anos'!D9>0,('📊 Projeção 3 Anos'!E9-'📊 Projeção 3 Anos'!D9)/'📊 Projeção 3 Anos'!D9,0)>=0.8,"✅ Alta velocidade",IF(IF('📊 Projeção 3 Anos'!D9>0,('📊 Projeção 3 Anos'!E9-'📊 Projeção 3 Anos'!D9)/'📊 Projeção 3 Anos'!D9,0)>=0.4,"🟡 Moderado","🔴 Lento")) -> ✅ Alta velocidade
B25: 📚 Glossário: MRR=Receita mensal | ARR=MRR×12 | CAC=Custo de aquisição | LTV=Valor vitalício do cliente | Churn=Cancelamento | EBITDA=Lucro operacional | Runway=Sobrevida do caixa

Sheet 📚 Guia Investidores
B1: GUIA: O QUE UM INVESTIDOR ANALISA EM UM MVP
B2: Indicador | C2: Por que importa? | D2: Benchmark de referência
B3: MRR / ARR | C3: Mede o tamanho real do negócio recorrente. É o primeiro número que um VC olha. Crescimento >20% ao mês indica tração. | D3: Early-stage: MRR >R$50K Série A: ARR >R$2M
B4: Churn Rate | C4: Se o produto não retém clientes, não há negócio escalável. Alto churn = problema de product-market fit. | D4: < 2%/mês (SaaS B2B) < 5%/mês (SaaS B2C)
B5: LTV / CAC | C5: Mede eficiência do modelo: para cada R$1 gasto em aquisição, quanto retorna? < 3x sinaliza modelo insustentável. | D5: > 3x aceitável > 5x excelente
B6: Payback Period | C6: Quanto tempo para recuperar o CAC. Curto payback = negócio mais eficiente e escalável com menos capital. | D6: < 12 meses (ideal < 6)
B7: Margem Bruta | C7: % da receita que sobra após COGS. Indica escalabilidade — negócio com 70%+ pode crescer sem custo proporcional. | D7: SaaS: 60–80% Marketplace: 40–60%
B8: EBITDA / Burn | C8: Quanto o negócio gera ou consome de caixa operacionalmente. Negativo é ok no início, mas precisa ter caminho claro. | D8: Positivo no Ano 2 ou 3
B9: Runway | C9: Quantos meses de vida o caixa garante. < 12 meses = zona de perigo. Indica quando a próxima captação é necessária. | D9: > 18 meses pós-rodada
B10: Crescimento YoY | C10: Taxa de crescimento ano a ano da receita. Principal indicador de momentum para VCs. Define valuation. | D10: 100–300% Seed 80–150% Série A
B11: NRR (Net Revenue Retention) | C11: % da receita de clientes do ano anterior que se manteve + expansão. > 100% = crescimento sem novos clientes. | D11: > 100% (best-in-class >120%)
B12: TAM / SAM / SOM | C12: Tamanho do mercado endereçável. Investidor precisa ver potencial de escala suficiente para retorno. | D12: TAM >R$1B SOM realista em 3–5 anos
